postgres_mcp/__init__.py
postgres_mcp/__version__.py
postgres_mcp/models.py
postgres_mcp/postgres_client.py
postgres_mcp/security.py
postgres_mcp/server.py
postgres_mcp/settings.py
postgres_mcp/utils.py
postgresql_mcp-0.2.0.dist-info/METADATA
postgresql_mcp-0.2.0.dist-info/WHEEL
postgresql_mcp-0.2.0.dist-info/entry_points.txt
postgresql_mcp-0.2.0.dist-info/licenses/LICENSE
postgresql_mcp-0.2.0.dist-info/RECORD
