Metadata-Version: 2.4
Name: postgresql-mcp
Version: 0.2.0
Summary: MCP server for PostgreSQL database operations - query, explore schemas, and analyze tables
Project-URL: Homepage, https://github.com/JaviMaligno/postgres_mcp
Project-URL: Documentation, https://github.com/JaviMaligno/postgres_mcp#readme
Project-URL: Repository, https://github.com/JaviMaligno/postgres_mcp
Project-URL: Bug Tracker, https://github.com/JaviMaligno/postgres_mcp/issues
Author-email: Javier Aguilar <javiecija96@gmail.com>
License: MIT
License-File: LICENSE
Keywords: ai,claude,database,llm,mcp,postgres,postgresql
Classifier: Development Status :: 4 - Beta
Classifier: Intended Audience :: Developers
Classifier: License :: OSI Approved :: MIT License
Classifier: Operating System :: OS Independent
Classifier: Programming Language :: Python :: 3
Classifier: Programming Language :: Python :: 3.10
Classifier: Programming Language :: Python :: 3.11
Classifier: Programming Language :: Python :: 3.12
Classifier: Topic :: Database
Classifier: Topic :: Software Development :: Libraries :: Python Modules
Requires-Python: >=3.10
Requires-Dist: mcp>=1.0.0
Requires-Dist: psycopg2-binary>=2.9.9
Requires-Dist: pydantic-settings>=2.0
Requires-Dist: pydantic>=2.0
Requires-Dist: python-dotenv>=1.0.0
